Dizcord/__init__.py
Dizcord/source.py
Dizcord-0.1.dist-info/LICENCE.txt
Dizcord-0.1.dist-info/METADATA
Dizcord-0.1.dist-info/WHEEL
Dizcord-0.1.dist-info/top_level.txt
Dizcord-0.1.dist-info/RECORD
