Metadata-Version: 2.1
Name: Dizcord
Version: 0.1
Summary: Useful Package To Style Prints, and commands for Discord.
Author: KADIUM
Author-email: jungshangx@gmail.com
Classifier: Programming Language :: Python :: 3
Classifier: License :: OSI Approved :: MIT License
Classifier: Operating System :: OS Independent
License-File: LICENCE.txt
